{
  "likes": 138,
  "id": 39224,
  "slug": "erika-senft-miller",
  "title": "Erika Senft Miller",
  "createdAt": 1581292800,
  "tags": [
    "Culture & Education",
    "Web & Interactive",
    "Animation",
    "Portfolio",
    "Unusual Navigation",
    "Black",
    "White",
    "Yellow",
    "Experimental",
    "Gallery",
    "Filters and Effects"
  ],
  "type": "submission",
  "url": "https://www.awwwards.com/sites/erika-senft-miller",
  "skills": {
    "design": 92,
    "html": 60,
    "css": 72,
    "angular": 53,
    "nodejs": false
  },
  "images": {
    "thumbnail": "/projects/images/thumbnails/5e3183a117e99237474589.png",
    "src": "/projects/images/5e3183a117e99237474589.png",
    "filename": "5e3183a117e99237474589.png"
  }
}